{
  "rooms": [
    [
      {
        "chest": null,
        "enemies": []
      },
      {
        "chest": {
          "items": ["healing herb", "iron dagger"]
        },
        "enemies": ["boss"]
      },
      {
        "chest": null,
        "enemies": ["goblin"]
      }
    ],
    [
      {
        "chest": null,
        "enemies": ["boss"]
      },
      {
        "chest": {
          "items": ["iron dagger"]
        },
        "enemies": []
      },
      {
        "chest": {
          "items": ["mana potion", "healing herb"]
        },
        "enemies": ["bandit"]
      }
    ]
  ]
}
